README.rst
setup.py
jrss/__init__.py
jrss/jrss.py
jrss.egg-info/PKG-INFO
jrss.egg-info/SOURCES.txt
jrss.egg-info/dependency_links.txt
jrss.egg-info/entry_points.txt
jrss.egg-info/requires.txt
jrss.egg-info/top_level.txt