Metadata-Version: 1.0
Name: jrss
Version: 0.1
Summary: Torrent RSS downloader
Home-page: https://github.com/spillevink/jrss
Author: Jakob Hedman
Author-email: jakob@hedman.email
License: GNU GPLv3
Platform: UNKNOWN
